{
  "themes": [
    {
      "theme": "New Wave of No-Code Tools Empowering Designers",
      "post_id": [
        "1h9w4i8"
      ],
      "url": "https://i.redd.it/l75e6pjbnp5e1.jpeg"
    },
    {
      "theme": "Rising Relevance of UX/UI Skills in Job Market",
      "post_id": [
        "1hs5x9l"
      ],
      "url": "https://www.reddit.com/r/UX_Design/comments/1hs5x9l/data_analyst_or_ux_designer/"
    },
    {
      "theme": "Legal Considerations for Product Portfolios",
      "post_id": [
        "1hghsk4"
      ],
      "url": "https://www.reddit.com/r/UX_Design/comments/1hghsk4/i_need_help/"
    },
    {
      "theme": "Holistic Design Practices Shifting Away from Silos",
      "post_id": [
        "1hpiw2h"
      ],
      "url": "https://www.reddit.com/r/productdesign/comments/1hpiw2h/how_does_the_design_process_for_complex_moulded/"
    }
  ]
}